consolexyz/__init__.py
consolexyz/console.py
consolexyz-0.0.2.dist-info/METADATA
consolexyz-0.0.2.dist-info/WHEEL
consolexyz-0.0.2.dist-info/top_level.txt
consolexyz-0.0.2.dist-info/RECORD
