Metadata-Version: 2.1
Name: consolexyz
Version: 0.0.2
Summary: My short description
Home-page: https://github.com/leitemaximiano/consolexyz
Author: Maximiano Leite
Author-email: macio.pb.cg@gmail.com
License: UNKNOWN
Platform: UNKNOWN
Requires-Python: >=3.8
